sv/src/period_ctrl.sv
// period_ctrl.sv 
// SystemVerilog version of period control module for 4-period shot clock display
// Inputs: clk, nrst (active-low reset), increment (advance period)
// Outputs: period_state (2 bits), period_leds (one-hot for each period)

module period_ctrl (
    input  logic clk,
    input  logic nrst,           // Active-low reset
    input  logic increment,      // Pulse to advance period
    output logic [1:0] period_state, // 2 bits: 0-3 for 4 periods
    output logic [3:0] period_leds   // One-hot LED for each period
);

always_ff @(posedge clk or negedge nrst) begin
    if (!nrst) begin
        period_state <= 2'b00;
    end else if (increment) begin
        if (period_state < 2'b11)
            period_state <= period_state + 1'b1;
        // Optionally, hold at 3 or wrap to 0
    end
end

always_comb begin
    case (period_state)
        2'b00: period_leds = 4'b0001;
        2'b01: period_leds = 4'b0010;
        2'b10: period_leds = 4'b0100;
        2'b11: period_leds = 4'b1000;
        default: period_leds = 4'b0000;
    endcase
end

endmodule

sv/tb/period_ctrl_tb.sv
`timescale 1ns/1ps
module tb_period_ctrl;
  // 10 ns clock
  reg clk = 0;
  always #5 clk = ~clk;

  reg nrst = 0;
  reg increment = 0;
  wire [1:0] period_state;
  wire [3:0] period_leds;

  period_ctrl dut (
    .clk(clk),
    .nrst(nrst),
    .increment(increment),
    .period_state(period_state),
    .period_leds(period_leds)
  );

  initial begin
    nrst = 0;
    // Enable VCD waveform dump for GTKWave / viewers
    $dumpfile("period.vcd");
    $dumpvars(0, tb_period_ctrl);

    #100; nrst = 1;
    $display("%0t: reset released", $time);

    // Pulse increment 6 times to observe wrapping/limit
    repeat (6) begin
      @(posedge clk);
      increment = 1;
      @(posedge clk);
      increment = 0;
      repeat (2) @(posedge clk);
      $display("%0t: period_state=%b period_leds=%b", $time, period_state, period_leds);
    end

    #100; $display("Period control test complete"); $finish;
  end
endmodule

period.vcd
$date
	Sat Mar 28 17:34:42 2026
$end
$version
	Icarus Verilog
$end
$timescale
	1ps
$end
$scope module tb_period_ctrl $end
$var wire 2 ! period_state [1:0] $end
$var wire 4 " period_leds [3:0] $end
$var reg 1 # clk $end
$var reg 1 $ increment $end
$var reg 1 % nrst $end
$scope module dut $end
$var wire 1 # clk $end
$var wire 1 $ increment $end
$var wire 1 % nrst $end
$var reg 4 & period_leds [3:0] $end
$var reg 2 ' period_state [1:0] $end
$upscope $end
$upscope $end
$enddefinitions $end
$comment Show the parameter values. $end
$dumpall
$end
#0
$dumpvars
bx '
b0 &
0%
0$
0#
b0 "
bx !
$end
#5000
b1 "
b1 &
b0 !
b0 '
1#
#10000
0#
#15000
1#
#20000
0#
#25000
1#
#30000
0#
#35000
1#
#40000
0#
#45000
1#
#50000
0#
#55000
1#
#60000
0#
#65000
1#
#70000
0#
#75000
1#
#80000
0#
#85000
1#
#90000
0#
#95000
1#
#100000
0#
1%
#105000
b10 "
b10 &
b1 !
b1 '
1$
1#
#110000
0#
#115000
0$
1#
#120000
0#
#125000
1#
#130000
0#
#135000
1#
#140000
0#
#145000
b100 "
b100 &
b10 !
b10 '
1$
1#
#150000
0#
#155000
0$
1#
#160000
0#
#165000
1#
#170000
0#
#175000
1#
#180000
0#
#185000
b1000 "
b1000 &
b11 !
b11 '
1$
1#
#190000
0#
#195000
0$
1#
#200000
0#
#205000
1#
#210000
0#
#215000
1#
#220000
0#
#225000
1$
1#
#230000
0#
#235000
0$
1#
#240000
0#
#245000
1#
#250000
0#
#255000
1#
#260000
0#
#265000
1$
1#
#270000
0#
#275000
0$
1#
#280000
0#
#285000
1#
#290000
0#
#295000
1#
#300000
0#
#305000
1$
1#
#310000
0#
#315000
0$
1#
